mcw/__init__.py
mcw/cmake.py
mcw/commandtool.py
mcw/logging.py
mcw/main.py
mcw/meson.py
mcw/ninja.py
mcw/server.py
mcw/util.py
meson_cmake_wrapper-0.3.3.dist-info/LICENSE
meson_cmake_wrapper-0.3.3.dist-info/METADATA
meson_cmake_wrapper-0.3.3.dist-info/WHEEL
meson_cmake_wrapper-0.3.3.dist-info/entry_points.txt
meson_cmake_wrapper-0.3.3.dist-info/top_level.txt
meson_cmake_wrapper-0.3.3.dist-info/RECORD
