Metadata-Version: 2.1
Name: meson-cmake-wrapper
Version: 0.3.3
Summary: Build system wrapper that provides Meson integration in CMake IDE's
Home-page: http://github.com/prozum/meson-cmake-wrapper
Author: Niclas Moeslund Overby
Author-email: noverby@prozum.dk
License: MIT license
Platform: UNKNOWN
Requires-Python: >=3.5
